MANIFEST.in
setup.py
jsonstore/__init__.py
jsonstore/client.py
jsonstore/dsl.py
jsonstore/exceptions.py
jsonstore/operators.py
jsonstore/rest.py
jsonstore/rison.py
jsonstore/run.py
jsonstore/store.py
jsonstore/webhook.py
jsonstore.egg-info/PKG-INFO
jsonstore.egg-info/SOURCES.txt
jsonstore.egg-info/dependency_links.txt
jsonstore.egg-info/entry_points.txt
jsonstore.egg-info/not-zip-safe
jsonstore.egg-info/requires.txt
jsonstore.egg-info/top_level.txt