Metadata-Version: 1.0
Name: jsonstore
Version: 1.3
Summary: JSONStore is a lightweight database for JSON documents exposed through HTTP.
Home-page: http://code.dealmeida.net/jsonstore
Author: Roberto De Almeida
Author-email: roberto@dealmeida.net
License: MIT
Platform: UNKNOWN
